<?xml version="1.0" encoding="utf-8"?>
<ExecutableTestSuite xmlns="http://www.interactive-instruments.de/etf/2.0"
	xmlns:xsi="http://www.w3.org/2001/XMLSchema-instance" id="EIDeab289c0-47c0-4b4f-bd11-1f49ecd21878" xsi:schemaLocation="http://www.interactive-instruments.de/etf/2.0 https://resources.etf-validator.net/schema/v2/val/ignoreRef.xsd">
	<itemHash>bQ==</itemHash>
	<remoteResource>https://github.com/inspire-eu-validation/ets-repository/tree/master/data-bu/bu-as</remoteResource>
	<localPath>/auto</localPath>
	<label>Conformance class: Application schema, Buildings</label>
	<description><![CDATA[This test suite examines requirements associated with the application schema.<br/><br/>
<b>This is a draft version. It has limitations and is expected to contain errors.</b> Please report any issues or problems <a href="https://github.com/inspire-eu-validation/community/wiki/Your-feedback" target="_blank">in GitHub</a>.<br/><br/>
Known limitations are documented in the description of the applicable test case or test assertion. There is a general limitation in all assertions that extensions in additional application schemas are only supported, if the unqualified name of the feature type in the extension is the same as the name of the feature type in the INSPIRE application schema.<br/><br/>
Source: <a href="http://inspire.ec.europa.eu/id/ats/data-bu/master/bu-as" target="_blank">Conformance Class 'Application Schema, Buildings'</a><br/><br/>
Pre-requisite conformance classes:
<ul><li><a href="http://inspire.ec.europa.eu/id/ats/data-bu/master/bu-gml" target="_blank">Conformance Class 'GML application schemas, Buildings'</a></li></ul>]]></description>
	<reference>../../inspire-noggeo-bsxets.xq</reference>
	<version>0.1.0</version>
	<author>Consortium Bilbomatica, Guadaltel y Geograma</author>
	<creationDate>2020-09-30T14:45:00Z</creationDate>
	<lastEditor>Consortium Bilbomatica, Guadaltel y Geograma</lastEditor>
	<lastUpdateDate>2020-09-30T14:45:00Z</lastUpdateDate>
	<tags>
		<tag ref="EIDae91aeb9-5fd2-43b6-a678-11c17f5ad63c"/>
	</tags>
	<testDriver ref="EID4dddc9e2-1b21-40b7-af70-6a2d156ad130"/>
	<translationTemplateBundle ref="EID70a263c0-0ad7-42f2-9d4d-0d8a4ca71b52"/>
	<ParameterList name="ETF Standard Parameters for XML test objects">
		<parameter name="files_to_test" required="true">
			<defaultValue>.*</defaultValue>
			<description ref="TR.filesToTest"/>
			<allowedValues>.*</allowedValues>
			<type>string</type>
		</parameter>
		<parameter name="tests_to_execute" required="false">
			<defaultValue>.*</defaultValue>
			<description ref="TR.testsToExecute"/>
			<allowedValues>.*</allowedValues>
			<type>string</type>
		</parameter>
	</ParameterList>
	<supportedTestObjectTypes>
		<testObjectType ref="EIDe1d4a306-7a78-4a3b-ae2d-cf5f0810853e"/>
	</supportedTestObjectTypes>
	<dependencies>
		<executableTestSuite ref="EID4f7e4a81-3bab-4058-b528-afec8d6e980d"/>
	</dependencies>
	<testModules>
		<TestModule id="EIDf447f3c8-b290-49dd-885e-6990faec8756">
			<label>IGNORE</label>
			<description>IGNORE</description>
			<parent ref="EIDeab289c0-47c0-4b4f-bd11-1f49ecd21878"/>
			<testCases>
				<TestCase id="EID3dfdcaeb-c000-4123-8414-cded45c40e35">
					<label>Code lists</label>
					<description>Verify that code lists extensions can be accessed.</description>
					<parent ref="EIDf447f3c8-b290-49dd-885e-6990faec8756"/>
					<testSteps>
						<TestStep id="EID8080cf98-fe7d-49cf-80fa-d8ba506f2d38">
							<label>IGNORE</label>
							<description>IGNORE</description>
							<parent ref="EID3dfdcaeb-c000-4123-8414-cded45c40e35"/>
							<statementForExecution>not applicable</statementForExecution>
							<testItemType ref="EIDf483e8e8-06b9-4900-ab36-adad0d7f22f0"/>
							<testAssertions>
								<TestAssertion id="EID0f127eaf-434e-49e2-995e-e4a445cb00ae">
									<label>bu-as.a.1: conditionOfConstruction</label>
									<description><![CDATA[When an attribute has a code list as its type, verify that the values comply with the definitions and include the values set out in Annex II, III and IV of the Implementing Rule. To pass this test verify that any instance of an attribute:
<ul>
<li>takes only values explicitly specified in the INSPIRE code list register when the code list‘s extensibility is 'none'.</li>
<li>takes only a value explicitly specified in the INSPIRE code list register or shall take a value that is narrower (i.e. more specific) than those explicitly specified in the application schema when the code list‘s extensibility is 'narrower'.</li>
<li>takes values explicitly specified in the INSPIRE code list register when the code list‘s extensibility is 'open' or if a value is not one of the values listed in the code list register check that any extensions do not overlap with the code lists that are defined in Annexes II, III and IV of the Implementing Rule and that all extensions conform to the requirements (This last check is a manual test).</li>
</ul>
<br/><br/>The following checks are performed for every feature in the dataset, for the not extensible codelists:
<ul><li>Check that all the <a href = 'http://inspire.ec.europa.eu/id/ats/data-bu/master/bu-as/code-list-values#conditionOfConstruction'> conditionOfConstruction</a> elements has a xlink:href attribute pointing to a <a href='http://inspire.ec.europa.eu/id/ats/data-bu/master/bu-as/code-list-values#validValue1'>valid value</a>. If the check fails report disallowedCodeListValue.</li></ul><br/><br/>
Source: <a href="http://inspire.ec.europa.eu/id/ats/data-bu/master/bu-as/code-list-values" target="_blank">Abstract Test Case 'Code list values'</a>, <a href="http://inspire.ec.europa.eu/documents/Data_Specifications/INSPIRE_DataSpecification_BU_v3.0.pdf">INSPIRE Data Specification on Buildings, A.1.3</a>]]></description>
									<parent ref="EID8080cf98-fe7d-49cf-80fa-d8ba506f2d38"/>
									<expectedResult>NOT_APPLICABLE</expectedResult>
									<expression>
let $codelist := 'http://inspire.ec.europa.eu/codelist/ConditionOfConstructionValue'
let $codelisturl := 'https://inspire.ec.europa.eu/codelist/ConditionOfConstructionValue/ConditionOfConstructionValue.en.xml'
let $valid_href := fn:doc($codelisturl)/*:codelist/*:containeditems/*:value/@id
let $property_string := 'conditionOfConstructionValue'
let $features_selected := $features[self::bu-core2d:Building | self::bu-core2d:BuildingPart | self::bu-core3d:Building | self::bu-core3d:BuildingPart]

let $messages := 

	for $feature in $features_selected
		let $envDom := $feature/bu-base:conditionOfConstruction

		return
			if (not(exists($envDom))) then
				local:addMessage('TR.missingElementBuildings',  map {'filename': local:filename($feature), 'featureType':local-name($feature), 'gmlid': string($feature/@*:id), 'property': $property_string})
			else if (count($envDom) > 1) then
				local:addMessage('TR.wrongMultiplicityBuildings',  map {'filename': local:filename($feature), 'featureType':local-name($feature), 'gmlid': string($feature/@*:id), 'property': $property_string, 'multiplicity': 1, 'count': count($envDom)})	
			else if (exists($envDom) and exists($envDom/@xlink:href) and not($envDom/@xlink:href = $valid_href)) then
				local:addMessage('TR.disallowedCodeListValueBuildings',  map {'filename': local:filename($feature), 'featureType':local-name($feature), 'gmlid': string($feature/@*:id), 'property': $property_string, 'value': string($envDom/@xlink:href), 'codelist': $codelist})
			else ()


let $messages_parts := 
	let $this_features :=
		for $this_feature in $features_selected
			return
				if (name($this_feature) = 'bu-core3d:Building') then
					$this_feature/bu-base:parts/bu-core3d:BuildingPart
				else if (name($this_feature) = 'bu-core2d:Building') then
					$this_feature/bu-base:parts/bu-core2d:BuildingPart
				else ()

	for $feature in $this_features
		let $envDom := $feature/bu-base:conditionOfConstruction

		return
			if (not(exists($envDom))) then
				local:addMessage('TR.missingElementBuildings',  map {'filename': local:filename($feature), 'featureType':local-name($feature/../..), 'gmlid': string($feature/../../@*:id), 'property': $property_string})
			else if (count($envDom) > 1) then
				local:addMessage('TR.wrongMultiplicityBuildings',  map {'filename': local:filename($feature), 'featureType':local-name($feature/../..), 'gmlid': string($feature/../../@*:id), 'property': $property_string, 'multiplicity': 1, 'count': count($envDom)})	
			else if (exists($envDom) and exists($envDom/@xlink:href) and not($envDom/@xlink:href = $valid_href)) then
				local:addMessage('TR.disallowedCodeListValueBuildings',  map {'filename': local:filename($feature/../..), 'featureType':local-name($feature/../..), 'gmlid': string($feature/../../@*:id), 'property': $property_string, 'value': string($envDom/@xlink:href), 'codelist': $codelist})
			else ()


let $combined_messages := ($messages, $messages_parts)

return
(if ($combined_messages) then 'FAILED' else 'PASSED',
local:error-statistics('TR.recordsWithErrors', count(fn:distinct-values($combined_messages//etf:argument[@token='id']/text()))),
$combined_messages)

									</expression>
									<testItemType ref="EIDf0edc596-49d2-48d6-a1a1-1ac581dcde0a"/>
									<translationTemplates>
										<translationTemplate ref="TR.missingElementBuildings"/>
										<translationTemplate ref="TR.wrongMultiplicityBuildings"/>
										<translationTemplate ref="TR.disallowedCodeListValueBuildings"/>
									</translationTemplates>
								</TestAssertion>

							</testAssertions>
						</TestStep>
					</testSteps>
				</TestCase>
			</testCases>
		</TestModule>
	</testModules>
</ExecutableTestSuite>