<TranslationTemplateBundle xmlns="http://www.interactive-instruments.de/etf/2.0"
	id="EIDfa68eb83-a25a-4009-84dd-036de4539c93"
	xmlns:xsi="http://www.w3.org/2001/XMLSchema-instance"
	xsi:schemaLocation="http://www.interactive-instruments.de/etf/2.0 https://resources.etf-validator.net/schema/v2/service/service.xsd">
	<translationTemplateCollections>
		<LangTranslationTemplateCollection name="TR.multiplicityShallBeOne">
			<translationTemplates>
				<TranslationTemplate language="en" name="TR.multiplicityShallBeOne">The multiplicity of '{element}' shall be one.</TranslationTemplate>
			</translationTemplates>
		</LangTranslationTemplateCollection>
		<LangTranslationTemplateCollection name="TR.multiplicityShallBeZeroOrOne">
			<translationTemplates>
				<TranslationTemplate language="en" name="TR.multiplicityShallBeZeroOrOne">The multiplicity of '{element}' shall be zero or one.</TranslationTemplate>
			</translationTemplates>
		</LangTranslationTemplateCollection>
		<LangTranslationTemplateCollection name="TR.multiplicityShallBeOneOrMore">
			<translationTemplates>
				<TranslationTemplate language="en" name="TR.multiplicityShallBeOneOrMore">The multiplicity of '{element}' shall be one or more.</TranslationTemplate>
			</translationTemplates>
		</LangTranslationTemplateCollection>
		<LangTranslationTemplateCollection name="TR.valueShallNotBeEmpty">
			<translationTemplates>
				<TranslationTemplate language="en" name="TR.valueShallNotBeEmpty">The value of '{element}' shall not be empty.</TranslationTemplate>
			</translationTemplates>
		</LangTranslationTemplateCollection>
		<LangTranslationTemplateCollection name="TR.valueShallBe">
			<translationTemplates>
				<TranslationTemplate language="en" name="TR.valueShallBe">The value of '{element}' shall be '{value}'.</TranslationTemplate>
			</translationTemplates>
		</LangTranslationTemplateCollection>
		<LangTranslationTemplateCollection name="TR.onlineResourceLink">
			<translationTemplates>
				<TranslationTemplate language="en" name="TR.onlineResourceLink">OnlineResource shall have an 'xlink:href' attribute pointing to an url.</TranslationTemplate>
			</translationTemplates>
		</LangTranslationTemplateCollection>
		<LangTranslationTemplateCollection name="TR.invalidSpatialDataServiceType">
			<translationTemplates>
				<TranslationTemplate language="en" name="TR.invalidSpatialDataServiceType">The value of spatialDataServiceType shall be 'view'.</TranslationTemplate>
			</translationTemplates>
		</LangTranslationTemplateCollection>
		<LangTranslationTemplateCollection name="TR.atLeastOneKeywordInClassification">
			<translationTemplates>
				<TranslationTemplate language="en" name="TR.atLeastOneKeywordInClassification">At least one keyword shall be a "Classification of Spatial data Services" (Part D.4 from INS MD).</TranslationTemplate>
			</translationTemplates>
		</LangTranslationTemplateCollection>
		<LangTranslationTemplateCollection name="TR.keywordsInKeywordList">
			<translationTemplates>
				<TranslationTemplate language="en" name="TR.keywordsInKeywordList">When more than Keyword exists, they shall be children of KeywordList node.</TranslationTemplate>
			</translationTemplates>
		</LangTranslationTemplateCollection>
		<LangTranslationTemplateCollection name="TR.atLeastOneDateType">
			<translationTemplates>
				<TranslationTemplate language="en" name="TR.atLeastOneDateType">At least one DateOfPublication, DateOfLastRevision or DateOfCreation element shall be provided.</TranslationTemplate>
			</translationTemplates>
		</LangTranslationTemplateCollection>
		<LangTranslationTemplateCollection name="TR.wrongConformityDegree">
			<translationTemplates>
				<TranslationTemplate language="en" name="TR.wrongConformityDegree">Degree of conformity shall be 'notEvaluated', 'conformant' or 'notConformant'.</TranslationTemplate>
			</translationTemplates>
		</LangTranslationTemplateCollection>
		<LangTranslationTemplateCollection name="TR.wrongContactPosition">
			<translationTemplates>
				<TranslationTemplate language="en" name="TR.wrongContactPosition">The provided ContactPosition '{value}' is not valid. The ContactPosition shall be one of the following values: 'resourceProvider', 'custodian', 'owner', 'user', 'distributor', 'originator', 'pointOfContact', 'principalInvestigator', 'processor', 'publisher' or 'author'.</TranslationTemplate>
			</translationTemplates>
		</LangTranslationTemplateCollection>
		<LangTranslationTemplateCollection name="TR.wrongDateFormat">
			<translationTemplates>
				<TranslationTemplate language="en" name="TR.wrongDateFormat">Date shall be in YYYY-MM-DD format.</TranslationTemplate>
			</translationTemplates>
		</LangTranslationTemplateCollection>
		<LangTranslationTemplateCollection name="TR.wrongGetMapMetadataImageFormat">
			<translationTemplates>
				<TranslationTemplate language="en" name="TR.wrongGetMapMetadataImageFormat">Either PNG ('image/png') or GIF ('image/gif') format shall be supported.</TranslationTemplate>
			</translationTemplates>
		</LangTranslationTemplateCollection>
		<LangTranslationTemplateCollection name="TR.duplicatedBoundingBox">
			<translationTemplates>
				<TranslationTemplate language="en" name="TR.duplicatedBoundingBox">The BoundingBox elements defined in the same layer shall not refer to the same CRS.</TranslationTemplate>
			</translationTemplates>
		</LangTranslationTemplateCollection>
		<LangTranslationTemplateCollection name="TR.missingCRSForBoundingBox">
			<translationTemplates>
				<TranslationTemplate language="en" name="TR.missingCRSForBoundingBox">A BoundingBox is provided for non existing CRS '{crs}' either in the layer itself nor in a parent layer.</TranslationTemplate>
			</translationTemplates>
		</LangTranslationTemplateCollection>
		<LangTranslationTemplateCollection name="TR.missingAuthorityURL">
			<translationTemplates>
				<TranslationTemplate language="en" name="TR.missingAuthorityURL">An AuthorityURL node shall exists.</TranslationTemplate>
			</translationTemplates>
		</LangTranslationTemplateCollection>
		<LangTranslationTemplateCollection name="TR.missingAuthorityURLname">
			<translationTemplates>
				<TranslationTemplate language="en" name="TR.missingAuthorityURLname">The AuthorityURL node shall have a 'name' attribute.</TranslationTemplate>
			</translationTemplates>
		</LangTranslationTemplateCollection>
		<LangTranslationTemplateCollection name="TR.missingAuthorityURLOnlineResource">
			<translationTemplates>
				<TranslationTemplate language="en" name="TR.missingAuthorityURLOnlineResource">The AuthorityURL node shall have an OnlineResource child with a non empty xlink:href attribute.</TranslationTemplate>
			</translationTemplates>
		</LangTranslationTemplateCollection>
		<LangTranslationTemplateCollection name="TR.authorityURLnameAlreadyDefined">
			<translationTemplates>
				<TranslationTemplate language="en" name="TR.authorityURLnameAlreadyDefined">The AuthorityURL name has been defined previously in a parent layer.</TranslationTemplate>
			</translationTemplates>
		</LangTranslationTemplateCollection>
		<LangTranslationTemplateCollection name="TR.layersWithoutIdentifier">
			<translationTemplates>
				<TranslationTemplate language="en" name="TR.layersWithoutIdentifier">Every layer shall have an Identifier node.</TranslationTemplate>
			</translationTemplates>
		</LangTranslationTemplateCollection>
		<LangTranslationTemplateCollection name="TR.unavailableAuthorityURL">
			<translationTemplates>
				<TranslationTemplate language="en" name="TR.unavailableAuthorityURL">A layer's Identifier mention an authority not defined in an available AuthorityURL element.</TranslationTemplate>
			</translationTemplates>
		</LangTranslationTemplateCollection>
		<LangTranslationTemplateCollection name="TR.notUniqueLayerAuthorityIdentifier">
			<translationTemplates>
				<TranslationTemplate language="en" name="TR.notUniqueLayerAuthorityIdentifier">A layer's Identifier has a non unique value for its authority.</TranslationTemplate>
			</translationTemplates>
		</LangTranslationTemplateCollection>
		<LangTranslationTemplateCollection name="TR.notUniqueLayerName">
			<translationTemplates>
				<TranslationTemplate language="en" name="TR.notUniqueLayerName">A layer's Name has a non unique value.</TranslationTemplate>
			</translationTemplates>
		</LangTranslationTemplateCollection>
		<LangTranslationTemplateCollection name="TR.notHarmonisedValue">
			<translationTemplates>
				<TranslationTemplate language="en" name="TR.notHarmonisedValue">The following layers do not have a correct name according with the harmonised layer names given in the INSPIRE collection: '{layerid}'.</TranslationTemplate>
			</translationTemplates>
		</LangTranslationTemplateCollection>
		<LangTranslationTemplateCollection name="TR.notUniqueLayerStyleName">
			<translationTemplates>
				<TranslationTemplate language="en" name="TR.notUniqueLayerStyleName">A layer's style has a non unique value for its Name.</TranslationTemplate>
			</translationTemplates>
		</LangTranslationTemplateCollection>
		<LangTranslationTemplateCollection name="TR.getMapNoMandatoryParameter">
			<translationTemplates>
				<TranslationTemplate language="en" name="TR.getMapNoMandatoryParameter">A GetMap was requested without a mandatory parameter and the service did not throw an exception.</TranslationTemplate>
			</translationTemplates>
		</LangTranslationTemplateCollection>
		<LangTranslationTemplateCollection name="TR.getMapWrongParameter">
			<translationTemplates>
				<TranslationTemplate language="en" name="TR.getMapWrongParameter">A GetMap was requested using parameter '{parameter}' with an invalid value and the service did not throw an exception.</TranslationTemplate>
			</translationTemplates>
		</LangTranslationTemplateCollection>
		<LangTranslationTemplateCollection name="TR.reponseLanguageDifferentThanRequested">
			<translationTemplates>
				<TranslationTemplate language="en" name="TR.reponseLanguageDifferentThanRequested">The capabilities response language is not the same as requested language.</TranslationTemplate>
			</translationTemplates>
		</LangTranslationTemplateCollection>
		<LangTranslationTemplateCollection name="TR.languageNotISO">
			<translationTemplates>
				<TranslationTemplate language="en" name="TR.languageNotISO">The language provided in the ExtendedCapabilities section is not a valid ISO 639-2/B alpha 3 code.</TranslationTemplate>
			</translationTemplates>
		</LangTranslationTemplateCollection>
		<LangTranslationTemplateCollection name="TR.reponseLanguageShallBeDefault">
			<translationTemplates>
				<TranslationTemplate language="en" name="TR.reponseLanguageShallBeDefault">The response language in ExtendedCapabilities shall be the same as default when an invalid language is requested.</TranslationTemplate>
			</translationTemplates>
		</LangTranslationTemplateCollection>
		<LangTranslationTemplateCollection name="TR.reponseTitleAbstractShallBeDefault">
			<translationTemplates>
				<TranslationTemplate language="en" name="TR.reponseTitleAbstractShallBeDefault">The response Title and Abstract shall be the same as default ones when default or invalid language is requested.</TranslationTemplate>
			</translationTemplates>
		</LangTranslationTemplateCollection>
		<LangTranslationTemplateCollection name="TR.reponseLanguageShallBeSameAsRequested">
			<translationTemplates>
				<TranslationTemplate language="en" name="TR.reponseLanguageShallBeSameAsRequested">A GetCapabilities with a supported language '{requestedlanguage}' as parameter was requested but the service language response was '{responselanguage}'.</TranslationTemplate>
			</translationTemplates>
		</LangTranslationTemplateCollection>
		<LangTranslationTemplateCollection name="TR.missingDefaultStyle">
			<translationTemplates>
				<TranslationTemplate language="en" name="TR.missingDefaultStyle">A layer does not provide a valid default style name as specified in its INSPIRE Data Specification.</TranslationTemplate>
			</translationTemplates>
		</LangTranslationTemplateCollection>
		<LangTranslationTemplateCollection name="TR.getMapSupportedFormat">
			<translationTemplates>
				<TranslationTemplate language="en" name="TR.getMapSupportedFormat">Not found image format in capabilities document to perform a GetMap request.</TranslationTemplate>
			</translationTemplates>
		</LangTranslationTemplateCollection>
		<LangTranslationTemplateCollection name="TR.cascadedLayerMetadata">
			<translationTemplates>
				<TranslationTemplate language="en" name="TR.cascadedLayerMetadata">A cascaded layer url metadata did not response a correct metadata document.</TranslationTemplate>
			</translationTemplates>
		</LangTranslationTemplateCollection>
		<LangTranslationTemplateCollection name="TR.notXMLResponse">
			<translationTemplates>
				<TranslationTemplate language="en" name="TR.notXMLResponse">The response to an http request was not a xml document.</TranslationTemplate>
			</translationTemplates>
		</LangTranslationTemplateCollection>
		<LangTranslationTemplateCollection name="TR.noMandatoryParameterNotFail">
			<translationTemplates>
				<TranslationTemplate language="en" name="TR.noMandatoryParameterNotFail">A GetCapabilities was requested without mandatory parameter '{parameter}' and the service did not throw an exception.</TranslationTemplate>
			</translationTemplates>
		</LangTranslationTemplateCollection>
		<LangTranslationTemplateCollection name="TR.wrongParameterNotFail">
			<translationTemplates>
				<TranslationTemplate language="en" name="TR.wrongParameterNotFail">A GetCapabilities was requested using parameter '{parameter}' with an invalid value and the service did not throw an exception.</TranslationTemplate>
			</translationTemplates>
		</LangTranslationTemplateCollection>
		<LangTranslationTemplateCollection name="TR.manual.testManual09">
			<translationTemplates>
				<TranslationTemplate language="en" name="TR.manual.testManual09">If a metadata for the view service exists, check manually that is referenced from MetadataUrl element of the ExtendedCapabilities section.</TranslationTemplate>
			</translationTemplates>
		</LangTranslationTemplateCollection>
		<LangTranslationTemplateCollection name="TR.manual.testManual13">
			<translationTemplates>
				<TranslationTemplate language="en" name="TR.manual.testManual13">Check manually if the metadata for a layer exists. If it does, Check manually if the url of the layer's metadata is provided in the 'xlink:href' attribute of an OnlineResource element of the layer.</TranslationTemplate>
			</translationTemplates>
		</LangTranslationTemplateCollection>
		<LangTranslationTemplateCollection name="TR.manual.testManual19">
			<translationTemplates>
				<TranslationTemplate language="en" name="TR.manual.testManual19">Check manually that EX_GeographicBoundingBox is the minimum bounding box for the data provided by the service.</TranslationTemplate>
			</translationTemplates>
		</LangTranslationTemplateCollection>
		<LangTranslationTemplateCollection name="TR.manual.testManual40">
			<translationTemplates>
				<TranslationTemplate language="en" name="TR.manual.testManual40">Check manually if a geographical coordinate system based on ETRS89 is used in continental Europe or ITRS outside continental Europe.</TranslationTemplate>
			</translationTemplates>
		</LangTranslationTemplateCollection>
		<LangTranslationTemplateCollection name="TR.manual.testManual43">
			<translationTemplates>
				<TranslationTemplate language="en" name="TR.manual.testManual43">For each Layer element with no associated default style, check if the applied style based on the geometry type match with: Point: grey square, 6 pixels; Curve: black solid line, 1 pixel; Surface: black solid line, 1 pixel, grey fill.</TranslationTemplate>
			</translationTemplates>
		</LangTranslationTemplateCollection>
		<LangTranslationTemplateCollection name="TR.manual.testManual44">
			<translationTemplates>
				<TranslationTemplate language="en" name="TR.manual.testManual44">Send a getMap request to the service endpoint with an empty STYLE parameter. Check manually if the style used in the response is the default style defined for the requested layer.</TranslationTemplate>
			</translationTemplates>
		</LangTranslationTemplateCollection>
		<LangTranslationTemplateCollection name="TR.manual.testManual47">
			<translationTemplates>
				<TranslationTemplate language="en" name="TR.manual.testManual47">Check manually that the provided legend is in the correct language.</TranslationTemplate>
			</translationTemplates>
		</LangTranslationTemplateCollection>
		<LangTranslationTemplateCollection name="TR.manual.testManual63">
			<translationTemplates>
				<TranslationTemplate language="en" name="TR.manual.testManual63">If cascaded layers exist, check manually that cascaded layers have a 'cascaded' attribute.</TranslationTemplate>
			</translationTemplates>
		</LangTranslationTemplateCollection>
		<LangTranslationTemplateCollection name="TR.manual.testManual64">
			<translationTemplates>
				<TranslationTemplate language="en" name="TR.manual.testManual64">If cascaded layers exist, check manually that the 'cascaded' attribute of cascaded layers is an integer number incremented by 1.</TranslationTemplate>
			</translationTemplates>
		</LangTranslationTemplateCollection>
		<LangTranslationTemplateCollection name="TR.manual.testManual65">
			<translationTemplates>
				<TranslationTemplate language="en" name="TR.manual.testManual65">If cascaded layers exists, check manually that the TRANSPARENT parameter of all layers is true and BGCOLOR parameter of all layers is the same.</TranslationTemplate>
			</translationTemplates>
		</LangTranslationTemplateCollection>
		<LangTranslationTemplateCollection name="TR.manual.testManual67">
			<translationTemplates>
				<TranslationTemplate language="en" name="TR.manual.testManual67">For each supported language, check manually if the natural language fields of the response are in the requested language.</TranslationTemplate>
			</translationTemplates>
		</LangTranslationTemplateCollection>
		<LangTranslationTemplateCollection name="TR.invalidSchema">
			<translationTemplates>
				<TranslationTemplate language="en" name="TR.invalidSchema">Schema not valid: {error}</TranslationTemplate>
			</translationTemplates>
		</LangTranslationTemplateCollection>
		
		<LangTranslationTemplateCollection name="TR.getMapNoMandatoryParameterNotFail">
			<translationTemplates>
				<TranslationTemplate language="en" name="TR.getMapNoMandatoryParameterNotFail">A GetMap was requested without mandatory parameter '{parameter}' and the service did not throw an exception.</TranslationTemplate>
			</translationTemplates>
		</LangTranslationTemplateCollection>
		<LangTranslationTemplateCollection name="TR.getMapWrongParameterNotFail">
			<translationTemplates>
				<TranslationTemplate language="en" name="TR.getMapWrongParameterNotFail">A GetMap was requested using parameter '{parameter}' with an invalid value and the service did not throw an exception.</TranslationTemplate>
			</translationTemplates>
		</LangTranslationTemplateCollection>
        <LangTranslationTemplateCollection name="TR.getMapResponseWithEmptyStyleParameterNotImage">
			<translationTemplates>
				<TranslationTemplate language="en" name="TR.getMapResponseWithEmptyStyleParameterNotImage">A GetMap was requested with empty 'style' parameter and the service did not response an image.</TranslationTemplate>
			</translationTemplates>
		</LangTranslationTemplateCollection>
        <LangTranslationTemplateCollection name="TR.fallbackInfo">
            <translationTemplates>
                <TranslationTemplate language="en" name="TR.fallbackInfo">The server experienced a several unexpected error. Please, try again later. If the problem persist, please contact with the helpdesk.</TranslationTemplate>
            </translationTemplates>
        </LangTranslationTemplateCollection>
	</translationTemplateCollections>
</TranslationTemplateBundle>
